nepalikit/__init__.py
nepalikit/manage_stopwords/__init__.py
nepalikit/manage_stopwords/manage_stopwords.py
nepalikit/preprocessing/TextProcessor.py
nepalikit/preprocessing/__init__.py
nepalikit/preprocessing/urls_emails.py
nepalikit/sentence_operation/__init__.py
nepalikit/sentence_operation/extract_sentences.py
nepalikit/sentence_operation/load_abbreviation.py
nepalikit/sentence_operation/normalize_text.py
nepalikit/sentence_operation/replace_abbreviations.py
nepalikit/sentence_operation/segment_sentences.py
nepalikit/sentence_operation/sentence_stats.py
nepalikit/tokenization/__init__.py
nepalikit/tokenization/sentencepiece_tokenizer.py
nepalikit/tokenization/tokenizer.py
nepalikit/tokenization/sentencepiece/model/NepaliKit_sentencepiece.model
nepalikit/utils/__init__.py
nepalikit/utils/utils.py
nepalikit-1.0.2.dist-info/METADATA
nepalikit-1.0.2.dist-info/WHEEL
nepalikit-1.0.2.dist-info/entry_points.txt
nepalikit-1.0.2.dist-info/top_level.txt
nepalikit-1.0.2.dist-info/RECORD
