Metadata-Version: 2.1
Name: nepalikit
Version: 1.0.2
Summary: A Nepali language processing library
Home-page: https://github.com/prabhashj07/nepalikit.git
Author: Prabhash Kumar Jha
Author-email: prabhashj07@gmail.com
License: MIT
Project-URL: Bug Reports, https://github.com/prabhashj07/nepalikit/issues
Project-URL: Source, https://github.com/prabhashj07/nepalikit/
Classifier: Programming Language :: Python :: 3
Classifier: Programming Language :: Python :: 3.7
Classifier: Programming Language :: Python :: 3.8
Classifier: Programming Language :: Python :: 3.9
Classifier: License :: OSI Approved :: MIT License
Classifier: Operating System :: OS Independent
Classifier: Natural Language :: Nepali
Classifier: Topic :: Text Processing :: Linguistic
Requires-Python: >=3.7
Requires-Dist: torch >=2.3.1
Requires-Dist: sentencepiece ==0.2.0
Requires-Dist: regex
